abdur_test_utilities/__init__.py
abdur_test_utilities/email_validator.py
abdur_test_utilities-0.3.dist-info/METADATA
abdur_test_utilities-0.3.dist-info/WHEEL
abdur_test_utilities-0.3.dist-info/top_level.txt
abdur_test_utilities-0.3.dist-info/RECORD
