Metadata-Version: 2.1
Name: abdur-test-utilities
Version: 0.3
Summary: A small utility for email validation.
Home-page: UNKNOWN
Author: Your Name
Author-email: your.email@example.com
License: UNKNOWN
Platform: UNKNOWN
Requires-Dist: pandas >=1.2.4
